setup.py
effectsizecalc/__init__.py
effectsizecalc.egg-info/PKG-INFO
effectsizecalc.egg-info/SOURCES.txt
effectsizecalc.egg-info/dependency_links.txt
effectsizecalc.egg-info/not-zip-safe
effectsizecalc.egg-info/requires.txt
effectsizecalc.egg-info/top_level.txt