Metadata-Version: 1.0
Name: effectsizecalc
Version: 3.2
Summary: Tool for calculating effect size between group means
Home-page: https://github.com/sudiptatung/EffectSizeCalculator.git
Author: Sudipta Tung
Author-email: sudiptatung@gmail.com
License: MIT
Platform: UNKNOWN
